bitshares/__init__.py
bitshares/account.py
bitshares/amount.py
bitshares/asset.py
bitshares/bitshares.py
bitshares/block.py
bitshares/blockchain.py
bitshares/blockchainobject.py
bitshares/committee.py
bitshares/dex.py
bitshares/exceptions.py
bitshares/genesisbalance.py
bitshares/htlc.py
bitshares/instance.py
bitshares/market.py
bitshares/memo.py
bitshares/message.py
bitshares/notify.py
bitshares/price.py
bitshares/proposal.py
bitshares/storage.py
bitshares/transactionbuilder.py
bitshares/utils.py
bitshares/vesting.py
bitshares/wallet.py
bitshares/witness.py
bitshares/worker.py
bitshares/aio/__init__.py
bitshares/aio/account.py
bitshares/aio/amount.py
bitshares/aio/asset.py
bitshares/aio/bitshares.py
bitshares/aio/block.py
bitshares/aio/blockchain.py
bitshares/aio/blockchainobject.py
bitshares/aio/committee.py
bitshares/aio/dex.py
bitshares/aio/genesisbalance.py
bitshares/aio/htlc.py
bitshares/aio/instance.py
bitshares/aio/market.py
bitshares/aio/memo.py
bitshares/aio/message.py
bitshares/aio/price.py
bitshares/aio/proposal.py
bitshares/aio/transactionbuilder.py
bitshares/aio/vesting.py
bitshares/aio/wallet.py
bitshares/aio/witness.py
bitshares/aio/worker.py
bitsharesapi/__init__.py
bitsharesapi/bitsharesnoderpc.py
bitsharesapi/exceptions.py
bitsharesapi/websocket.py
bitsharesbase/__init__.py
bitsharesbase/account.py
bitsharesbase/asset_permissions.py
bitsharesbase/bip38.py
bitsharesbase/chains.py
bitsharesbase/memo.py
bitsharesbase/objects.py
bitsharesbase/objecttypes.py
bitsharesbase/operationids.py
bitsharesbase/operations.py
bitsharesbase/signedtransactions.py
bitsharesbase/transactions.py
tests/__init__.py
tests/brokeninstance.py
tests/fixtures.py
tests/test_account.py
tests/test_amount.py
tests/test_asset.py
tests/test_base_objects.py
tests/test_bitshares.py
tests/test_block.py
tests/test_blockchain.py
tests/test_connection.py
tests/test_extensions.py
tests/test_fee.py
tests/test_memo.py
tests/test_message.py
tests/test_object.py
tests/test_objectcache.py
bitshares-0.7.1.dist-info/LICENSE.txt
bitshares-0.7.1.dist-info/METADATA
bitshares-0.7.1.dist-info/WHEEL
bitshares-0.7.1.dist-info/top_level.txt
bitshares-0.7.1.dist-info/RECORD
